compressio/__init__.py
compressio/compress.py
compressio/diagnostics.py
compressio/formatter.py
compressio/py.typed
compressio/type_compressor.py
compressio/typing.py
compressio/utils.py
compressio/version.py
compressio/compression_algorithms/__init__.py
compressio/compression_algorithms/type_compressions.py
compressio-0.1.4.dist-info/LICENSE
compressio-0.1.4.dist-info/METADATA
compressio-0.1.4.dist-info/WHEEL
compressio-0.1.4.dist-info/top_level.txt
compressio-0.1.4.dist-info/RECORD
