Metadata-Version: 2.1
Name: compressio
Version: 0.1.4
Summary: compressio
Home-page: https://github.com/dylan-profiler/compressio
Author: Ian Eaves, Simon Brugman
Author-email: ian.k.eaves@gmail.com
License: UNKNOWN
Platform: UNKNOWN
Classifier: Programming Language :: Python :: 3
Classifier: Programming Language :: Python :: 3.6
Classifier: Programming Language :: Python :: 3.7
Classifier: Programming Language :: Python :: 3.8
Requires-Python: >=3.6
Requires-Dist: visions (>=0.6.0)
Requires-Dist: pint
Requires-Dist: pandas
Requires-Dist: numpy
